piedemo/__init__.py
piedemo/__main__.py
piedemo/auto.py
piedemo/cache.py
piedemo/ngrok_utils.py
piedemo/page.py
piedemo/web.py
piedemo/webdemo.py
piedemo/__pycache__/__init__.cpython-36.pyc
piedemo/__pycache__/__init__.cpython-37.pyc
piedemo/__pycache__/__main__.cpython-36.pyc
piedemo/__pycache__/__main__.cpython-37.pyc
piedemo/__pycache__/auto.cpython-37.pyc
piedemo/__pycache__/cache.cpython-36.pyc
piedemo/__pycache__/cache.cpython-37.pyc
piedemo/__pycache__/ngrok_utils.cpython-36.pyc
piedemo/__pycache__/ngrok_utils.cpython-37.pyc
piedemo/__pycache__/page.cpython-37.pyc
piedemo/__pycache__/web.cpython-37.pyc
piedemo/__pycache__/webdemo.cpython-37.pyc
piedemo/checkpoint/__init__.py
piedemo/checkpoint/archive.py
piedemo/checkpoint/gdrive.py
piedemo/checkpoint/mega_path.py
piedemo/checkpoint/mega_url.py
piedemo/checkpoint/path.py
piedemo/checkpoint/pretrained_checkpoint.py
piedemo/checkpoint/pretrained_jit_model.py
piedemo/checkpoint/rclone.py
piedemo/checkpoint/url.py
piedemo/checkpoint/yadisk.py
piedemo/checkpoint/__pycache__/__init__.cpython-36.pyc
piedemo/checkpoint/__pycache__/__init__.cpython-37.pyc
piedemo/checkpoint/__pycache__/archive.cpython-36.pyc
piedemo/checkpoint/__pycache__/archive.cpython-37.pyc
piedemo/checkpoint/__pycache__/gdrive.cpython-36.pyc
piedemo/checkpoint/__pycache__/gdrive.cpython-37.pyc
piedemo/checkpoint/__pycache__/mega_path.cpython-36.pyc
piedemo/checkpoint/__pycache__/mega_path.cpython-37.pyc
piedemo/checkpoint/__pycache__/mega_url.cpython-36.pyc
piedemo/checkpoint/__pycache__/mega_url.cpython-37.pyc
piedemo/checkpoint/__pycache__/path.cpython-36.pyc
piedemo/checkpoint/__pycache__/path.cpython-37.pyc
piedemo/checkpoint/__pycache__/pretrained_checkpoint.cpython-36.pyc
piedemo/checkpoint/__pycache__/pretrained_checkpoint.cpython-37.pyc
piedemo/checkpoint/__pycache__/pretrained_jit_model.cpython-36.pyc
piedemo/checkpoint/__pycache__/pretrained_jit_model.cpython-37.pyc
piedemo/checkpoint/__pycache__/rclone.cpython-36.pyc
piedemo-2.0.6.dist-info/METADATA
piedemo-2.0.6.dist-info/WHEEL
piedemo-2.0.6.dist-info/top_level.txt
piedemo-2.0.6.dist-info/zip-safe
piedemo-2.0.6.dist-info/RECORD
