Metadata-Version: 2.1
Name: piedemo
Version: 2.0.6
Summary: PyTorch based Web Demo app
Home-page: https://github.com/PieDataLabs/piedemo
Author: George Kasparyants
Author-email: gg@piedata.ai
Platform: Darwin-21.4.0-x86_64-i386-64bit
Classifier: Intended Audience :: Developers
Classifier: Operating System :: OS Independent
Classifier: Topic :: Software Development :: Libraries :: Python Modules
Classifier: Programming Language :: Python
Classifier: Programming Language :: Python :: 3 :: Only
Classifier: Programming Language :: Python :: 3.6
Requires-Python: >=3.6,<3.9
Requires-Dist: flask
Requires-Dist: mega.py
Requires-Dist: pydrive
Requires-Dist: gdown
Requires-Dist: googledrivedownloader
Requires-Dist: wldhx.yadisk-direct
Requires-Dist: pandas
Requires-Dist: Pillow
Requires-Dist: numpy
Requires-Dist: scikit-image
Requires-Dist: parse
Requires-Dist: opencv-contrib-python
Requires-Dist: argostranslate
Requires-Dist: pyvis
Requires-Dist: networkx
